{
  "nightly": {
    "description": "nightly",
    "hide": false,
    "last_updated": "2024-02-14T12:10:42.000Z",
    "last_updated_url": "https://github.com/hotio/lidarr/actions/runs/7900801184",
    "latest": false,
    "tags": [
      "nightly",
      "nightly-2.2.0.4035",
      "nightly-7e2a56e"
    ]
  },
  "pr-artist-stats": {
    "description": "",
    "hide": true,
    "last_updated": "2024-02-14T12:10:42.000Z",
    "last_updated_url": "https://github.com/hotio/lidarr/actions/runs/7900801479",
    "latest": false,
    "tags": [
      "pr-artist-stats",
      "pr-artist-stats-2.1.7.4004",
      "pr-artist-stats-49bc7ff"
    ]
  },
  "release": {
    "description": "master",
    "hide": false,
    "last_updated": "2024-02-14T12:10:49.000Z",
    "last_updated_url": "https://github.com/hotio/lidarr/actions/runs/7900801788",
    "latest": true,
    "tags": [
      "release",
      "release-2.1.7.4030",
      "release-2e42b79"
    ]
  },
  "testing": {
    "description": "develop",
    "hide": false,
    "last_updated": "2024-02-14T12:10:56.000Z",
    "last_updated_url": "https://github.com/hotio/lidarr/actions/runs/7900802106",
    "latest": false,
    "tags": [
      "testing",
      "testing-2.1.7.4030",
      "testing-d37f3ea"
    ]
  }
}
